[
  {
    "Category": "Dashboards",
    "Navs": [
      {
        "Id":1,
        "Title": "Dashboards",
        "Icon": "mdi-trending-up",
        "Childs": [
          {
            "Id": 2,
            "Title": "eCommerce",
            "Icon": "mdi-circle",
            "Href": "/dashboards/ecommerce"
          },
          {
            "Id": 3,
            "Title": "Analytics",
            "Icon": "mdi-circle",
            "Href": "/dashboards/analytics"
          }
        ]
      }    
    ]
  },
  {
    "Category": "Apps",
    "Navs": [
      {
        "Id": 4,
        "Title": "eCommerce",
        "Icon": "mdi-cart-outline",
        "Childs": [
          {
            "Id": 5,
            "Title": "Shop",
            "Icon": "mdi-circle",
            "Href": "/apps/ecommerce/shop"
          },
          {
            "Id": 6,
            "Title": "Details",
            "Icon": "mdi-circle",
            "Href": "/apps/ecommerce/details"
          },
          {
            "Id": 7,
            "Title": "Order",
            "Icon": "mdi-circle",
            "Href": "/apps/ecommerce/order"
          }
        ]
      },
      {
        "Id": 8,
        "Title": "Todo",
        "Icon": "far fa-calendar-check",
        "Href": "/apps/todo"
      },
      {
        "Id": 9,
        "Title": "Invoice",
        "Icon": "mdi-content-paste",
        "Childs": [
          {
            "Id": 10,
            "Title": "List",
            "Icon": "mdi-circle",
            "Href": "/apps/invoice/list"
          },
          {
            "Id": 11,
            "Title": "Preview",
            "Icon": "mdi-circle",
            "Href": "/apps/invoice/preview"
          },
          {
            "Id": 12,
            "Title": "Edit",
            "Icon": "mdi-circle",
            "Href": "/apps/invoice/edit"
          },
          {
            "Id": 13,
            "Title": "Add",
            "Icon": "mdi-circle",
            "Href": "/apps/invoice/add"
          }
        ]
      },
      {
        "Id": 14,
        "Title": "User",
        "Icon": "far fa-user",
        "Childs": [
          {
            "Id": 15,
            "Title": "List",
            "Icon": "mdi-circle",
            "Href": "/apps/user/list"
          },
          {
            "Id": 16,
            "Title": "View",
            "Icon": "mdi-circle",
            "Href": "/apps/user/view"
          },
          {
            "Id": 17,
            "Title": "Edit",
            "Icon": "mdi-circle",
            "Href": "/apps/user/edit"
          }
        ]
      }
    ]
  },
  {
    "Category": "Pages",
    "Navs": [
      {
        "Id": 18,
        "Title": "Auth",
        "Icon": "mdi-file-outline",
        "Childs": [
          {
            "Id": 19,
            "Title": "Login v1",
            "Icon": "mdi-circle",
            "Href": "/pages/authentication/login-v1"
          },
          {
            "Id": 20,
            "Title": "Login v2",
            "Icon": "mdi-circle",
            "Href": "/pages/authentication/login-v2"
          },
          {
            "Id": 21,
            "Title": "Register v1",
            "Icon": "mdi-circle",
            "Href": "/pages/authentication/register-v1"
          },
          {
            "Id": 22,
            "Title": "Register v2",
            "Icon": "mdi-circle",
            "Href": "/pages/authentication/register-v2"
          },
          {
            "Id": 23,
            "Title": "Forgot Password v1",
            "Icon": "mdi-circle",
            "Href": "/pages/authentication/forgot-password-v1"
          },
          {
            "Id": 24,
            "Title": "Forgot Password v2",
            "Icon": "mdi-circle",
            "Href": "/pages/authentication/forgot-password-v2"
          },
          {
            "Id": 25,
            "Title": "Reset Password v1",
            "Icon": "mdi-circle",
            "Href": "/pages/authentication/reset-password-v1"
          },
          {
            "Id": 26,
            "Title": "Reset Password v2",
            "Icon": "mdi-circle",
            "Href": "/pages/authentication/reset-password-v2"
          }
        ]
      },
      {
        "Id": 27,
        "Title": "Others",
        "Icon": "mdi-dots-horizontal",
        "Childs": [
          {
            "Id": 28,
            "Title": "Account Settings",
            "Icon": "mdi-circle",
            "Href": "/pages/others/account-settings"
          },
          {
            "Id": 29,
            "Title": "500",
            "Icon": "mdi-circle",
            "Href": "/pages/others/500"
          },
          {
            "Id": 30,
            "Title": "401",
            "Icon": "mdi-circle",
            "Href": "/pages/others/401"
          },
          {
            "Id": 31,
            "Title": "404",
            "Icon": "mdi-circle",
            "Href": "/pages/others/404"
          }
        ]
      }
    ]
  }
]
